<?xml version="1.0"?>
<!DOCTYPE hibernate-mapping PUBLIC "-//Hibernate/Hibernate Mapping DTD 3.0//EN"
"http://hibernate.sourceforge.net/hibernate-mapping-3.0.dtd">
<!-- Generated Dec 3, 2015 8:53:03 AM by Hibernate Tools 3.4.0.CR1 -->
<hibernate-mapping>
    <class name="com.spring.hibernate.entities.Staff" table="STAFF">
        <id name="id" type="int">
            <column name="id" />
            <generator class="assigned" />
        </id>
        <property name="name" type="java.lang.String">
            <column name="name" />
        </property>
        <property name="authority" type="int">
            <column name="authority" />
        </property>
        <property name="username" type="java.lang.String">
            <column name="username" />
        </property>
        <property name="pwd" type="java.lang.String">
            <column name="pwd" />
        </property>
        <property name="telephone" type="java.lang.String">
            <column name="telephone" />
        </property>
    </class>
</hibernate-mapping>
